[
  {
    "id": "aja-00-1",
    "name": "Stekelenburg",
    "club": "Ajax",
    "era": "2000s",
    "positions": [
      "GK"
    ],
    "stats": {
      "goals": 0,
      "assists": 0,
      "cleanSheets": 12
    },
    "rating": 79,
    "source": "38-0.org"
  },
  {
    "id": "aja-00-2",
    "name": "Ibrahimovic",
    "club": "Ajax",
    "era": "2000s",
    "positions": [
      "ST"
    ],
    "stats": {
      "goals": 25,
      "assists": 5
    },
    "rating": 87,
    "source": "38-0.org"
  },
  {
    "id": "aja-00-3",
    "name": "Van Nistelrooy",
    "club": "Ajax",
    "era": "2000s",
    "positions": [
      "ST"
    ],
    "stats": {
      "goals": 26,
      "assists": 5
    },
    "rating": 86,
    "source": "38-0.org"
  },
  {
    "id": "aja-00-4",
    "name": "Sneijder",
    "club": "Ajax",
    "era": "2000s",
    "positions": [
      "CAM",
      "CM",
      "AM",
      "MF"
    ],
    "stats": {
      "goals": 10,
      "assists": 13
    },
    "rating": 87,
    "source": "38-0.org"
  },
  {
    "id": "aja-10-1",
    "name": "De Ligt",
    "club": "Ajax",
    "era": "2010s",
    "positions": [
      "CB",
      "DF"
    ],
    "stats": {
      "goals": 2,
      "assists": 4
    },
    "rating": 84,
    "source": "38-0.org"
  },
  {
    "id": "aja-10-2",
    "name": "Tadic",
    "club": "Ajax",
    "era": "2010s",
    "positions": [
      "LW",
      "ST",
      "CAM",
      "AM",
      "FW"
    ],
    "stats": {
      "goals": 24,
      "assists": 6
    },
    "rating": 84,
    "source": "38-0.org"
  },
  {
    "id": "aja-10-3",
    "name": "De Jong",
    "club": "Ajax",
    "era": "2010s",
    "positions": [
      "CM",
      "MF"
    ],
    "stats": {
      "goals": 8,
      "assists": 14
    },
    "rating": 86,
    "source": "38-0.org"
  },
  {
    "id": "aja-10-4",
    "name": "Onana",
    "club": "Ajax",
    "era": "2010s",
    "positions": [
      "GK"
    ],
    "stats": {
      "goals": 0,
      "assists": 0,
      "cleanSheets": 13
    },
    "rating": 81,
    "source": "38-0.org"
  },
  {
    "id": "aja-10-5",
    "name": "Tagliafico",
    "club": "Ajax",
    "era": "2010s",
    "positions": [
      "LB",
      "DF"
    ],
    "stats": {
      "goals": 3,
      "assists": 5
    },
    "rating": 82,
    "source": "38-0.org"
  },
  {
    "id": "aja-10-6",
    "name": "Mazraoui",
    "club": "Ajax",
    "era": "2010s",
    "positions": [
      "RB",
      "DF"
    ],
    "stats": {
      "goals": 3,
      "assists": 4
    },
    "rating": 81,
    "source": "38-0.org"
  },
  {
    "id": "aja-10-7",
    "name": "Blind",
    "club": "Ajax",
    "era": "2010s",
    "positions": [
      "CB",
      "CM",
      "MF",
      "DF"
    ],
    "stats": {
      "goals": 2,
      "assists": 5
    },
    "rating": 83,
    "source": "38-0.org"
  },
  {
    "id": "aja-10-8",
    "name": "Ziyech",
    "club": "Ajax",
    "era": "2010s",
    "positions": [
      "RW",
      "CAM",
      "AM",
      "FW"
    ],
    "stats": {
      "goals": 25,
      "assists": 6
    },
    "rating": 86,
    "source": "38-0.org"
  },
  {
    "id": "aja-10-9",
    "name": "Van de Beek",
    "club": "Ajax",
    "era": "2010s",
    "positions": [
      "CM",
      "CAM",
      "AM",
      "MF"
    ],
    "stats": {
      "goals": 10,
      "assists": 13
    },
    "rating": 83,
    "source": "38-0.org"
  },
  {
    "id": "aja-10-10",
    "name": "Promes",
    "club": "Ajax",
    "era": "2010s",
    "positions": [
      "LW",
      "ST",
      "FW"
    ],
    "stats": {
      "goals": 24,
      "assists": 5
    },
    "rating": 84,
    "source": "38-0.org"
  },
  {
    "id": "aja-20-1",
    "name": "Kudus",
    "club": "Ajax",
    "era": "2020s",
    "positions": [
      "CAM",
      "RW",
      "AM",
      "FW"
    ],
    "stats": {
      "goals": 10,
      "assists": 12
    },
    "rating": 82,
    "source": "38-0.org"
  },
  {
    "id": "aja-20-2",
    "name": "Brobbey",
    "club": "Ajax",
    "era": "2020s",
    "positions": [
      "ST"
    ],
    "stats": {
      "goals": 24,
      "assists": 5
    },
    "rating": 80,
    "source": "38-0.org"
  },
  {
    "id": "aja-20-3",
    "name": "Timber",
    "club": "Ajax",
    "era": "2020s",
    "positions": [
      "CB",
      "RB",
      "DF"
    ],
    "stats": {
      "goals": 2,
      "assists": 4
    },
    "rating": 81,
    "source": "38-0.org"
  },
  {
    "id": "por-00-1",
    "name": "Deco",
    "club": "Porto",
    "era": "2000s",
    "positions": [
      "CAM",
      "CM",
      "AM",
      "MF"
    ],
    "stats": {
      "goals": 10,
      "assists": 14
    },
    "rating": 88,
    "source": "38-0.org"
  },
  {
    "id": "por-00-2",
    "name": "Ricardo Carvalho",
    "club": "Porto",
    "era": "2000s",
    "positions": [
      "CB",
      "DF"
    ],
    "stats": {
      "goals": 2,
      "assists": 3
    },
    "rating": 85,
    "source": "38-0.org"
  },
  {
    "id": "por-00-3",
    "name": "Falcao",
    "club": "Porto",
    "era": "2000s",
    "positions": [
      "ST"
    ],
    "stats": {
      "goals": 25,
      "assists": 5
    },
    "rating": 86,
    "source": "38-0.org"
  },
  {
    "id": "por-00-4",
    "name": "Pepe",
    "club": "Porto",
    "era": "2000s",
    "positions": [
      "CB",
      "DF"
    ],
    "stats": {
      "goals": 2,
      "assists": 3
    },
    "rating": 85,
    "source": "38-0.org"
  },
  {
    "id": "por-10-1",
    "name": "Hulk",
    "club": "Porto",
    "era": "2010s",
    "positions": [
      "ST",
      "RW",
      "FW"
    ],
    "stats": {
      "goals": 25,
      "assists": 5
    },
    "rating": 87,
    "source": "38-0.org"
  },
  {
    "id": "por-10-2",
    "name": "Moutinho",
    "club": "Porto",
    "era": "2010s",
    "positions": [
      "CM",
      "CAM",
      "AM",
      "MF"
    ],
    "stats": {
      "goals": 9,
      "assists": 13
    },
    "rating": 84,
    "source": "38-0.org"
  },
  {
    "id": "por-10-3",
    "name": "Aboubakar",
    "club": "Porto",
    "era": "2010s",
    "positions": [
      "ST"
    ],
    "stats": {
      "goals": 24,
      "assists": 5
    },
    "rating": 82,
    "source": "38-0.org"
  },
  {
    "id": "por-10-4",
    "name": "Danilo",
    "club": "Porto",
    "era": "2010s",
    "positions": [
      "RB",
      "DF"
    ],
    "stats": {
      "goals": 2,
      "assists": 4
    },
    "rating": 81,
    "source": "38-0.org"
  },
  {
    "id": "por-20-1",
    "name": "Taremi",
    "club": "Porto",
    "era": "2020s",
    "positions": [
      "ST"
    ],
    "stats": {
      "goals": 24,
      "assists": 5
    },
    "rating": 82,
    "source": "38-0.org"
  },
  {
    "id": "por-20-2",
    "name": "Diogo Costa",
    "club": "Porto",
    "era": "2020s",
    "positions": [
      "GK"
    ],
    "stats": {
      "goals": 0,
      "assists": 0,
      "cleanSheets": 12
    },
    "rating": 79,
    "source": "38-0.org"
  },
  {
    "id": "por-20-3",
    "name": "Otavio",
    "club": "Porto",
    "era": "2020s",
    "positions": [
      "CAM",
      "RW",
      "AM",
      "FW"
    ],
    "stats": {
      "goals": 10,
      "assists": 13
    },
    "rating": 82,
    "source": "38-0.org"
  },
  {
    "id": "ben-00-1",
    "name": "Simao",
    "club": "Benfica",
    "era": "2000s",
    "positions": [
      "LW",
      "RW",
      "FW"
    ],
    "stats": {
      "goals": 24,
      "assists": 5
    },
    "rating": 84,
    "source": "38-0.org"
  },
  {
    "id": "ben-00-2",
    "name": "Luisao",
    "club": "Benfica",
    "era": "2000s",
    "positions": [
      "CB",
      "DF"
    ],
    "stats": {
      "goals": 2,
      "assists": 3
    },
    "rating": 83,
    "source": "38-0.org"
  },
  {
    "id": "ben-00-3",
    "name": "Cardozo",
    "club": "Benfica",
    "era": "2000s",
    "positions": [
      "ST"
    ],
    "stats": {
      "goals": 25,
      "assists": 5
    },
    "rating": 83,
    "source": "38-0.org"
  },
  {
    "id": "ben-00-4",
    "name": "Aimar",
    "club": "Benfica",
    "era": "2000s",
    "positions": [
      "CAM",
      "CM",
      "AM",
      "MF"
    ],
    "stats": {
      "goals": 10,
      "assists": 14
    },
    "rating": 88,
    "source": "38-0.org"
  },
  {
    "id": "ben-10-1",
    "name": "Jonas",
    "club": "Benfica",
    "era": "2010s",
    "positions": [
      "ST"
    ],
    "stats": {
      "goals": 25,
      "assists": 5
    },
    "rating": 83,
    "source": "38-0.org"
  },
  {
    "id": "ben-10-2",
    "name": "Talisca",
    "club": "Benfica",
    "era": "2010s",
    "positions": [
      "CAM",
      "ST",
      "AM"
    ],
    "stats": {
      "goals": 10,
      "assists": 12
    },
    "rating": 83,
    "source": "38-0.org"
  },
  {
    "id": "ben-10-3",
    "name": "Garay",
    "club": "Benfica",
    "era": "2010s",
    "positions": [
      "CB",
      "DF"
    ],
    "stats": {
      "goals": 2,
      "assists": 3
    },
    "rating": 81,
    "source": "38-0.org"
  },
  {
    "id": "ben-20-1",
    "name": "Antonio Silva",
    "club": "Benfica",
    "era": "2020s",
    "positions": [
      "CB",
      "DF"
    ],
    "stats": {
      "goals": 2,
      "assists": 3
    },
    "rating": 81,
    "source": "38-0.org"
  },
  {
    "id": "ben-20-2",
    "name": "Rafa Silva",
    "club": "Benfica",
    "era": "2020s",
    "positions": [
      "CAM",
      "LW",
      "AM",
      "FW"
    ],
    "stats": {
      "goals": 10,
      "assists": 13
    },
    "rating": 85,
    "source": "38-0.org"
  },
  {
    "id": "ben-20-3",
    "name": "Trubin",
    "club": "Benfica",
    "era": "2020s",
    "positions": [
      "GK"
    ],
    "stats": {
      "goals": 0,
      "assists": 0,
      "cleanSheets": 12
    },
    "rating": 77,
    "source": "38-0.org"
  },
  {
    "id": "ben-20-4",
    "name": "Enzo Fernandez",
    "club": "Benfica",
    "era": "2020s",
    "positions": [
      "CM",
      "CAM",
      "AM",
      "MF"
    ],
    "stats": {
      "goals": 9,
      "assists": 14
    },
    "rating": 85,
    "source": "38-0.org"
  },
  {
    "id": "ben-20-5",
    "name": "Di Maria",
    "club": "Benfica",
    "era": "2020s",
    "positions": [
      "RW",
      "LW",
      "FW"
    ],
    "stats": {
      "goals": 25,
      "assists": 6
    },
    "rating": 86,
    "source": "38-0.org"
  },
  {
    "id": "ben-20-6",
    "name": "Otamendi",
    "club": "Benfica",
    "era": "2020s",
    "positions": [
      "CB",
      "DF"
    ],
    "stats": {
      "goals": 2,
      "assists": 3
    },
    "rating": 83,
    "source": "38-0.org"
  },
  {
    "id": "ben-20-7",
    "name": "Neres",
    "club": "Benfica",
    "era": "2020s",
    "positions": [
      "RW",
      "LW",
      "FW"
    ],
    "stats": {
      "goals": 24,
      "assists": 5
    },
    "rating": 83,
    "source": "38-0.org"
  },
  {
    "id": "ben-20-8",
    "name": "Pavlidis",
    "club": "Benfica",
    "era": "2020s",
    "positions": [
      "ST"
    ],
    "stats": {
      "goals": 24,
      "assists": 5
    },
    "rating": 82,
    "source": "38-0.org"
  },
  {
    "id": "ben-20-9",
    "name": "Florentino",
    "club": "Benfica",
    "era": "2020s",
    "positions": [
      "CM",
      "MF"
    ],
    "stats": {
      "goals": 7,
      "assists": 13
    },
    "rating": 83,
    "source": "38-0.org"
  },
  {
    "id": "ben-20-10",
    "name": "Bah",
    "club": "Benfica",
    "era": "2020s",
    "positions": [
      "LB",
      "RB",
      "DF"
    ],
    "stats": {
      "goals": 3,
      "assists": 4
    },
    "rating": 80,
    "source": "38-0.org"
  },
  {
    "id": "spo-20-1",
    "name": "Gyokeres",
    "club": "Sporting",
    "era": "2020s",
    "positions": [
      "ST"
    ],
    "stats": {
      "goals": 25,
      "assists": 5
    },
    "rating": 85,
    "source": "38-0.org"
  },
  {
    "id": "spo-20-2",
    "name": "Pedro Goncalves",
    "club": "Sporting",
    "era": "2020s",
    "positions": [
      "CAM",
      "LW",
      "AM",
      "FW"
    ],
    "stats": {
      "goals": 10,
      "assists": 13
    },
    "rating": 86,
    "source": "38-0.org"
  },
  {
    "id": "spo-20-3",
    "name": "Porro",
    "club": "Sporting",
    "era": "2020s",
    "positions": [
      "RB",
      "DF"
    ],
    "stats": {
      "goals": 3,
      "assists": 5
    },
    "rating": 81,
    "source": "38-0.org"
  },
  {
    "id": "spo-20-4",
    "name": "Coates",
    "club": "Sporting",
    "era": "2020s",
    "positions": [
      "CB",
      "DF"
    ],
    "stats": {
      "goals": 2,
      "assists": 4
    },
    "rating": 82,
    "source": "38-0.org"
  },
  {
    "id": "spo-20-5",
    "name": "Adan",
    "club": "Sporting",
    "era": "2020s",
    "positions": [
      "GK"
    ],
    "stats": {
      "goals": 0,
      "assists": 0,
      "cleanSheets": 12
    },
    "rating": 77,
    "source": "38-0.org"
  },
  {
    "id": "spo-20-6",
    "name": "Nunes",
    "club": "Sporting",
    "era": "2020s",
    "positions": [
      "LW",
      "RW",
      "FW"
    ],
    "stats": {
      "goals": 24,
      "assists": 5
    },
    "rating": 85,
    "source": "38-0.org"
  },
  {
    "id": "spo-20-7",
    "name": "Ugarte",
    "club": "Sporting",
    "era": "2020s",
    "positions": [
      "CM",
      "MF"
    ],
    "stats": {
      "goals": 7,
      "assists": 13
    },
    "rating": 84,
    "source": "38-0.org"
  },
  {
    "id": "spo-20-8",
    "name": "Edwards",
    "club": "Sporting",
    "era": "2020s",
    "positions": [
      "RW",
      "LW",
      "FW"
    ],
    "stats": {
      "goals": 24,
      "assists": 5
    },
    "rating": 82,
    "source": "38-0.org"
  },
  {
    "id": "spo-20-9",
    "name": "Inacio",
    "club": "Sporting",
    "era": "2020s",
    "positions": [
      "CB",
      "DF"
    ],
    "stats": {
      "goals": 2,
      "assists": 4
    },
    "rating": 82,
    "source": "38-0.org"
  },
  {
    "id": "spo-20-10",
    "name": "Hjulmand",
    "club": "Sporting",
    "era": "2020s",
    "positions": [
      "CM",
      "MF"
    ],
    "stats": {
      "goals": 8,
      "assists": 13
    },
    "rating": 82,
    "source": "38-0.org"
  },
  {
    "id": "por-20-4",
    "name": "Pepe",
    "club": "Porto",
    "era": "2020s",
    "positions": [
      "CB",
      "RB",
      "DF"
    ],
    "stats": {
      "goals": 2,
      "assists": 3
    },
    "rating": 81,
    "source": "38-0.org"
  }
]